mo/__init__.py
mo/__main__.py
mo/cli.py
mo/frontend.py
mo/io.py
mo/project.py
mo/runner.py
mo-0.2.0.dist-info/DESCRIPTION.rst
mo-0.2.0.dist-info/METADATA
mo-0.2.0.dist-info/RECORD
mo-0.2.0.dist-info/WHEEL
mo-0.2.0.dist-info/entry_points.txt
mo-0.2.0.dist-info/metadata.json
mo-0.2.0.dist-info/top_level.txt
tests/__init__.py
