Metadata-Version: 2.0
Name: mo
Version: 0.2.0
Summary: Incredibly simple YAML-based task runner.
Home-page: https://github.com/thomasleese/mo
Author: Thomas Leese
Author-email: inbox@thomasleese.me
License: UNKNOWN
Download-URL: https://github.com/thomasleese/mo/releases
Keywords: task,runner
Platform: UNKNOWN
Classifier: Development Status :: 3 - Alpha
Classifier: Environment :: Console
Classifier: Intended Audience :: Developers
Classifier: License :: OSI Approved :: MIT License
Classifier: Programming Language :: Python :: 3
Classifier: Topic :: Software Development :: Build Tools
Classifier: Topic :: Utilities
Requires-Dist: PyYAML
Requires-Dist: colorama
